{
    "name":"github.com/gsdocker/gsmake",

    "import" : [
        {"name" : "github.com/gsdocker/gsos","scope":"task|runtimes"},
        {"name" : "github.com/gsdocker/gserrors","scope":"task|runtimes"},
        {"name" : "github.com/gsdocker/gsconfig","scope":"task|runtimes"},
        {"name" : "github.com/gsdocker/gslogger","scope":"task|runtimes"}
    ],

    "task" : {

        "resources" :{
            "description":"prepare package's resources"
        },

        "compile" : {
            "prev" : "resources",
            "description":"compile package source codes"
        },

        "test" : {
            "prev" : "compile",
            "description":"run package's test suite"
        },

        "setup" : {
            "prev" : "test",
            "description":"install current package"
        },

        "cache":{
            "prev":"test",
            "description":"link develop package into gsmake cache space"
        },

        "list" : {"description":"list loade task"},

        "update" : {"description":"update cached package by scm"},

        "atom" : {"description":"start atom"}
    },

    "properties" : {
        "goinstall":[
            "cmd/gsmake"
        ]
    }
}
